{
    "key": "group_6072b91802943",
    "title": "Options",
    "fields": [
        {
            "key": "field_63ac586ca0ba2",
            "label": "Sticky CTA",
            "name": "",
            "aria-label": "",
            "type": "tab",
            "instructions": "",
            "required": 0,
            "conditional_logic": 0,
            "wrapper": {
                "width": "",
                "class": "",
                "id": ""
            },
            "placement": "top",
            "endpoint": 0
        },
        {
            "key": "field_6072b9257c171",
            "label": "Sticky CTA",
            "name": "sticky_cta",
            "aria-label": "",
            "type": "group",
            "instructions": "",
            "required": 0,
            "conditional_logic": 0,
            "wrapper": {
                "width": "",
                "class": "",
                "id": ""
            },
            "layout": "block",
            "sub_fields": [
                {
                    "key": "field_6072b95b7c172",
                    "label": "Sticky CTA Text",
                    "name": "sticky_cta_text",
                    "aria-label": "",
                    "type": "text",
                    "instructions": "",
                    "required": 0,
                    "conditional_logic": 0,
                    "wrapper": {
                        "width": "33",
                        "class": "",
                        "id": ""
                    },
                    "default_value": "",
                    "placeholder": "",
                    "prepend": "",
                    "append": "",
                    "maxlength": ""
                },
                {
                    "key": "field_6072b9687c173",
                    "label": "Sticky CTA URL",
                    "name": "sticky_cta_url",
                    "aria-label": "",
                    "type": "url",
                    "instructions": "",
                    "required": 0,
                    "conditional_logic": 0,
                    "wrapper": {
                        "width": "33",
                        "class": "",
                        "id": ""
                    },
                    "default_value": "",
                    "placeholder": ""
                },
                {
                    "key": "field_6072bb3fdac37",
                    "label": "Sticky CTA Show\/Hide",
                    "name": "sticky_cta_is_active",
                    "aria-label": "",
                    "type": "true_false",
                    "instructions": "Do you want this Sticky CTA to be shown on the live site?",
                    "required": 0,
                    "conditional_logic": 0,
                    "wrapper": {
                        "width": "33",
                        "class": "",
                        "id": ""
                    },
                    "message": "",
                    "default_value": 0,
                    "ui": 1,
                    "ui_on_text": "YES",
                    "ui_off_text": "NO"
                }
            ]
        },
        {
            "key": "field_63ac584176e1f",
            "label": "Front Page",
            "name": "",
            "aria-label": "",
            "type": "tab",
            "instructions": "",
            "required": 0,
            "conditional_logic": 0,
            "wrapper": {
                "width": "",
                "class": "",
                "id": ""
            },
            "placement": "top",
            "endpoint": 0
        },
        {
            "key": "field_60a409ad3a937",
            "label": "Front Page Popup Form URL",
            "name": "front_page_popup_form",
            "aria-label": "",
            "type": "text",
            "instructions": "looks like this...  <code> https:\/\/enviro.wantech.com.hk\/insight <\/code>",
            "required": 0,
            "conditional_logic": 0,
            "wrapper": {
                "width": "",
                "class": "",
                "id": ""
            },
            "default_value": "",
            "placeholder": "",
            "prepend": "",
            "append": "",
            "maxlength": ""
        },
        {
            "key": "field_6263fa35dec8e",
            "label": "Show Front Page Popup form",
            "name": "show_popup",
            "aria-label": "",
            "type": "true_false",
            "instructions": "Use this to stop the pop-up showing",
            "required": 0,
            "conditional_logic": 0,
            "wrapper": {
                "width": "",
                "class": "",
                "id": ""
            },
            "message": "",
            "default_value": 1,
            "ui": 1,
            "ui_on_text": "",
            "ui_off_text": ""
        },
        {
            "key": "field_63ab2cf788db9",
            "label": "Navigiation",
            "name": "",
            "aria-label": "",
            "type": "tab",
            "instructions": "",
            "required": 0,
            "conditional_logic": 0,
            "wrapper": {
                "width": "",
                "class": "",
                "id": ""
            },
            "placement": "top",
            "endpoint": 0
        },
        {
            "key": "field_63ab2d0588dba",
            "label": "Navigation Logo",
            "name": "nav_logo",
            "aria-label": "",
            "type": "image",
            "instructions": "",
            "required": 0,
            "conditional_logic": 0,
            "wrapper": {
                "width": "",
                "class": "",
                "id": ""
            },
            "return_format": "url",
            "library": "all",
            "min_width": "",
            "min_height": "",
            "min_size": "",
            "max_width": "",
            "max_height": "",
            "max_size": "",
            "mime_types": "",
            "preview_size": "medium"
        }
    ],
    "location": [
        [
            {
                "param": "options_page",
                "operator": "==",
                "value": "theme-options"
            }
        ]
    ],
    "menu_order": 0,
    "position": "normal",
    "style": "default",
    "label_placement": "top",
    "instruction_placement": "label",
    "hide_on_screen": "",
    "active": true,
    "description": "",
    "show_in_rest": 0,
    "modified": 1679779156
}